regional_observer_workbook/__init__.py
regional_observer_workbook/assets/2018/PS-4/column-totals.csv
regional_observer_workbook/assets/2018/PS-4/column-totals.npy
regional_observer_workbook/assets/2018/PS-4/form-fields.json
regional_observer_workbook/assets/2018/PS-4/page-totals.csv
regional_observer_workbook/assets/2018/PS-4/page-totals.npy
regional_observer_workbook/assets/2018/PS-4/page1.png
regional_observer_workbook/assets/2018/PS-4/sample-data.npy
regional_observer_workbook/assets/2018/PS-4/sampling-patterns.csv
regional_observer_workbook/assets/2018/PS-4/sampling-patterns.npy
regional_observer_workbook/assets/inventory.txt
regional_observer_workbook/cli/__init__.py
regional_observer_workbook/cli/utility.py
regional_observer_workbook/consts.py
regional_observer_workbook/errors.py
regional_observer_workbook/form_original.py
regional_observer_workbook/operations.py
regional_observer_workbook/py.typed
regional_observer_workbook-0.3.0.dist-info/licenses/LICENSE
regional_observer_workbook-0.3.0.dist-info/WHEEL
regional_observer_workbook-0.3.0.dist-info/entry_points.txt
regional_observer_workbook-0.3.0.dist-info/METADATA
regional_observer_workbook-0.3.0.dist-info/RECORD
