Metadata-Version: 2.4
Name: regional-observer-workbook
Version: 0.3.0
Summary: Library for working with scans of SPC/FFA regional observer workbooks
Author: Corey Cole
Author-email: Corey Cole <3700879+corey-cole@users.noreply.github.com>
License-Expression: MIT
License-File: LICENSE
Classifier: Development Status :: 4 - Beta
Classifier: Intended Audience :: Developers
Classifier: Programming Language :: Python :: 3
Classifier: Programming Language :: Python :: 3.12
Requires-Dist: opencv-python-headless>=4.12.0.88
Requires-Dist: pillow>=12.0.0
Requires-Python: >=3.12
